brandonpy/__init__.py
brandonpy/pkg1/__init__.py
brandonpy/pkg1/module1.py
brandonpy/pkg1/module2.py
brandonpy/pkg2/__init__.py
brandonpy/pkg2/modulea.py
brandonpy/pkg2/moduleb.py
brandonpy-0.0.1.dev1.dist-info/DESCRIPTION.rst
brandonpy-0.0.1.dev1.dist-info/METADATA
brandonpy-0.0.1.dev1.dist-info/RECORD
brandonpy-0.0.1.dev1.dist-info/WHEEL
brandonpy-0.0.1.dev1.dist-info/metadata.json
brandonpy-0.0.1.dev1.dist-info/top_level.txt
