Metadata-Version: 2.0
Name: brandonpy
Version: 0.0.1.dev1
Summary: A sample Python project
Home-page: https://github.com/byu-dml/brandonpy
Author: Brandon Schoenfeld
Author-email: bsjchoenfeld@byu.edu
License: MIT
Keywords: brandon brandonpy sample test
Platform: UNKNOWN
Classifier: Programming Language :: Python :: 3.5
Requires-Python: ~=3.5
Requires-Dist: tqdm
